[{"dirt":"Terra"},{"cobbled deepslate":"Pedregulho de ard\u00f3sia"},{"stone hoe":"Enxada de pedra"},{"moss block":"Bloco de musgo"},{"moss carpet":"Tapete de musgo"},{"azalea":"Azaleia"},{"stone bricks":"Tijolos de pedra"},{"cracked stone bricks":"Tijolos de pedra rachados"},{"mossy stone bricks":"Tijolos de pedra musgosos"},{"chiseled stone bricks":"Tijolos de pedra talhados"},{"spruce sapling":"Muda de pinheiro"},{"deepslate tiles":"Ladrilhos de ard\u00f3sia"},{"polished deepslate":"Ard\u00f3sia polida"},{"chiseled deepslate":"Ard\u00f3sia talhada"},{"spyglass":"Luneta"},{"bundle":"Bolsa"},{"amethyst cluster":"Agregado de ametista"},{"budding amethyst":"Drusa de ametista"},{"amethyst block":"Bloco de ametista"},{"glow ink sac":"Bolsa de tinta brilhante"},{"glow lichen":"L\u00edquen brilhante"},{"lodestone":"Magnetita"},{"ancient debris":"Detritos ancestrais"},{"netherite block":"Bloco de netherita"},{"netherite scrap":"Fragmentos de netherita"},{"netherite ingot":"Barra de netherita"},{"warped nylium":"Nic\u00e9lio distorcido"},{"crimson nylium":"Nic\u00e9lio carmesim"},{"netherrack":"Netherrack"},{"crimsom stem":"Caule carmesim"},{"warped stem":"Caule distorcido"},{"nether wart block":"Bloco de fungos do Nether"},{"shroomlight":"Cogubrilho"},{"crimson roots":"Ra\u00edzes carmesins"},{"warped roots":"Ra\u00edzes distorcidas"},{"crimson fungus":"Fungo carmesim"},{"warped fungus":"Fungo distorcido"},{"red mushroom":"Cogumelo vermelho"},{"brown mushroom":"Cogumelo marrom"},{"weeping vines":"Trepadeiras choronas"},{"soul soil":"Terra das almas"},{"soul sand":"Areia das almas"},{"blackstone":"Pedra-negra"},{"polished blackstone block":"Pedra-negra polida"},{"chiseled polished blackstone":"Pedra-negra polida talhada"},{"stone":"Pedra"},{"cobblestone":"Pedregulho"},{"furnace":"Fornalha"},{"blast furnace":"Alto-forno"},{"lectern":"Atril"},{"smithing table":"Bancada de ferraria"},{"fletching table":"Bancada de arco e flecha"},{"brewing stand":"Suporte de po\u00e7\u00f5es"},{"egg":"Ovo"},{"wheat":"Trigo"},{"pumpkin":"Ab\u00f3bora"},{"carved pumpkin":"Ab\u00f3bora esculpida"},{"jack o lantern":"Ab\u00f3bora de Halloween"},{"diamond":"Diamante"},{"diamond block":"Bloco de diamante"},{"gold ingot":"Barra de ouro"},{"gold ore":"Min\u00e9rio de ouro"},{"nether gold ore":"Min\u00e9rio de ouro do Nether"},{"gold nugget":"Pepita de ouro"},{"gold block":"Bloco de ouro"},{"rotten flesh":"Carne podre"},{"golden carrot":"Cenoura dourada"},{"golden apple":"Ma\u00e7\u00e3 dourada"},{"enchanted golden apple":"Ma\u00e7\u00e3 dourada encantada"},{"cooked mutton":"Carneiro assado"},{"cooked porkchop":"Costeleta de porco assada"},{"cooked salmon":"Salm\u00e3o assado"},{"cooked beef":"Fil\u00e9"},{"baked potato":"Batata assada"},{"beetroot soup":"Ensopado de beterraba"},{"honey bottle":"Frasco de mel"},{"cake":"Bolo"},{"cookie":"Biscoito"},{"sweet berries":"Bagas doces"},{"suspicious stew":"Ensopado suspeito"},{"rabbit stew":"Ensopado de coelho"},{"beef":"Bife cru"},{"podzol":"Podzol"},{"gravel":"Cascalho"},{"grass block":"Bloco de grama"},{"rooted dirt":"Terra enraizada"},{"coarse dirt":"Terra inf\u00e9rtil"},{"sand":"Areia"},{"red sand":"Areia vermelha"},{"sandstone":"Arenito"},{"red sandstone":"Arenito vermelho"},{"smooth sandstone":"Arenito liso"},{"smooth red sandstone":"Arenito vermelho liso"},{"chiseled sandstone":"Arenito talhado"},{"cut red sandstone":"Arenito vermelho lapidado"},{"cut sandstone":"Arenito lapidado"},{"chiseled red sandstone":"Arenito vermelho talhado"},{"red sandstone stairs":"Escadas de arenito vermelho"},{"smooth sandstone stairs":"Escadas de arenito liso"},{"sandstone stairs":"Escadas de arenito"},{"warped wart block":"Bloco de fungos distorcidos"},{"twisting vines":"Trepadeiras retorcidas"},{"nether sprouts":"Brotos do Nether"},{"glowstone":"Pedra luminosa"},{"cooked cod":"Bacalhau assado"},{"cod":"Bacalhau cru"},{"salmon":"Salm\u00e3o cru"},{"spawner":"Gerador"},{"barrier":"Barreira"},{"command block":"Bloco de comando"},{"end portal frame":"Moldura do portal do End"},{"bedrock":"Rocha-m\u00e3e"},{"tuff":"Tufo"},{"calcite":"Calcita"},{"obsidian":"Obsidiana"},{"crying obsidian":"Obsidiana chorona"},{"polished blackstone bricks":"Tijolos de pedra-negra polida"},{"cracked polished blackstone bricks":"Tijolos de pedra-negra polida rachados"},{"deepslate bricks":"Tijolos de ard\u00f3sia"},{"bowl":"Tigela"},{"glass bottle":"Frasco"},{"bucket":"Balde"},{"water bucket":"Balde de \u00e1gua"},{"lava bucket":"Balde de lava"},{"milk bucket":"Balde de leite"},{"cod bucket":"Balde com bacalhau"},{"tropical fish bucket":"balde com peixe tropical"},{"axolotl bucket":"Balde com axolote"},{"pufferfish bucket":"Balde com baiacu"},{"salmon bucket":"Balde com salm\u00e3o"},{"powder snow bucket":"Balde de neve fofa"},{"snow":"Neve"},{"snow block":"Bloco de neve"},{"ice":"Gelo"},{"packed ice":"Gelo compactado"},{"blue ice":"Gelo azul"},{"experience bottle":"Frasco de experi\u00eancia"},{"emerald":"Esmeralda"},{"emerald block":"Bloco de esmeralda"},{"emerald ore":"Min\u00e9rio de esmeralda"},{"iron ore":"Min\u00e9rio de ferro"},{"copper ore":"Min\u00e9rio de cobre"},{"redstone ore":"Min\u00e9rio de redstone"},{"deepslate redstone ore":"Min\u00e9rio de redstone de ard\u00f3dia"},{"deepslate emerald ore":"Min\u00e9rio de esmeralda de ard\u00f3sia"},{"deepslate diamond ore":"Min\u00e9rio de diamante de ard\u00f3sia"},{"diamond ore":"Min\u00e9rio de diamante"},{"coal ore":"Min\u00e9rio de carv\u00e3o"},{"deepslate coal ore":"Min\u00e9rio de carv\u00e3o de ard\u00f3sia"},{"lapis ore":"Min\u00e9rio de l\u00e1pis laz\u00fali"},{"deepslate lapis lazuli ore":"Min\u00e9rio de l\u00e1pis-laz\u00fali de ard\u00f3sia"},{"deepslate gold ore":"Min\u00e9rio de ouro de ard\u00f3sia"},{"nether quartz ore":"Min\u00e9rio de quartzo do Nether"},{"fishing rod":"Vara de pesca"},{"clock":"Rel\u00f3gio"},{"carrot on a stick":"Vara com cenoura"},{"warped fungus on a stick":"Vara com fungo distorcido"},{"flowering azalea":"Azaleia florescente"},{"smoker":"Defumador"},{"crafting table":"Bancada de trabalho"},{"redstone lamp":"L\u00e2mpada de redstone"},{"wooden sword":"Espada de madeira"},{"blaze rod":"Vara de blaze"},{"porkchop":"Costeleta de porco crua"},{"mutton":"Carneiro cru"},{"cooked chicken":"Frango assado"},{"chicken":"Frango cru"},{"poisonous potato":"Batata venenosa"},{"deepslate":"Ard\u00f3sia"},{"oak pressure plate":"Placa de press\u00e3o de carvalho"},{"stone pressure plate":"Placa de press\u00e3o de pedra"},{"warped pressure plate":"Placa de press\u00e3o distorcida"},{"redstone block":"Bloco de redstone"},{"target":"Alvo"},{"lightning rod":"Para-raios"},{"tnt":"Dinamite"},{"note block":"Bloco musical"},{"sculk sensor":"Sensor de sculk"},{"daylight detector":"Detector de luz solar"},{"dropper":"Liberador"},{"dispenser":"Ejetor"},{"slime block":"Bloco de slime"},{"honey block":"Bloco de mel"},{"scute":"Escama de tartaruga"},{"leather":"Couro"},{"gunpowder":"P\u00f3lvora"},{"flint and steel":"Pederneira"},{"flint":"S\u00edlex"},{"slime ball":"Bola de slime"},{"book":"Livro"},{"paper":"Papel"},{"clay ball":"Argila"},{"brick":"Tijolo"},{"snow ball":"Bola de neve"},{"feather":"Pena"},{"stick":"Graveto"},{"copper ingot":"Barra de cobre"},{"iron ingot":"Barra de ferro"},{"charcoal":"Carv\u00e3o vegetal"},{"coal":"Carv\u00e3o"},{"beacon":"Sinalizador"},{"conduit":"Aqueduto"},{"andesite":"Andesito"},{"hopper":"Funil"},{"crimson pressure plate":"Placa de press\u00e3o carmisim"},{"spruce pressure plate":"Placa de press\u00e3o de pinheiro"},{"birch pressure plate":"Placa de press\u00e3o de b\u00e9tula"},{"acacia pressure plate":"Placa de press\u00e3o de ac\u00e1cia"},{"dark oak pressure plate":"Placa de press\u00e3o de carvalho escuro"},{"polished blackstone pressure plate":"Placa de press\u00e3o de pedra-negra polida"},{"jungle pressure plate":"Placa de press\u00e3o de madeira da selva"},{"light weighted pressure plate":"Placa de press\u00e3o de pesagem pesada"},{"heavy weighted pressure plate":"Placa de press\u00e3o de pesagem leve"},{"redstone torch":"Tocha de redstone"},{"redstone dust":"P\u00f3 de redstone"},{"piston":"Pist\u00e3o"},{"sticky piston":"Pist\u00e3o grudento"},{"observer":"Observador"},{"lever":"Alavanca"},{"repeater":"Repetidor de redstone"},{"comparator":"Comparador de redstone"},{"trapped chest":"Ba\u00fa com armadilha"},{"tripwire hook":"Gancho de armadilha"},{"oak button":"Bot\u00e3o de carvalho"},{"birch button":"Bot\u00e3o de b\u00e9tula"},{"spruce button":"Bot\u00e3o de pinheiro"},{"acacia button":"Bot\u00e3o de ac\u00e1cia"},{"jungle button":"Bot\u00e3o de madeira da selva"},{"dark oak button":"Bot\u00e3o de carvalho escuro"},{"warped button":"Bot\u00e3o distorcido"},{"crimson button":"Bot\u00e3o carmesim"},{"stone button":"Bot\u00e3o de pedra"},{"polished blackstone button\t":"Bot\u00e3o de pedra-negra polida"},{"name tag":"Etiqueta"},{"lead":"La\u00e7o"},{"shears":"Tesoura"},{"string":"Linha"},{"turtle egg":"Ovo de tartaruga"},{"wheat seeds":"Sementes de trigo"},{"ink sac":"Bolsa de tinta"},{"deepslate iron ore":"Min\u00e9rio de ferro de ard\u00f3sia"},{"deepslate copper ore":"Min\u00e9rio de cobre de ard\u00f3sia"},{"raw iron":"Ferro bruto"},{"raw copper":"Cobre bruto"},{"raw gold":"Ouro bruto"},{"glow squid spawn egg":"Ovo gerador de lula-brilhante"},{"axolotl spawn egg":"Ovo gerador de axolote"},{"bee nest":"Colmeia"},{"beehive":"Colmeia artificial"},{"bee spawn egg":"Ovo gerador de abelha"},{"honeycomb":"Favo de mel"},{"honeycomb block":"Bloco de favo de mel"},{"wooden pickaxe":"Picareta de madeira"},{"stone pickaxe":"Picareta de pedra"},{"iron pickaxe":"Picareta de ferro"},{"golden pickaxe":"Picareta de ouro"},{"diamond pickaxe":"Picareta de diamante"},{"netherite pickaxe":"Picareta de netherita"},{"stone sword":"Espada de pedra"},{"iron sword":"Espada de ferro"},{"golden sword":"Espada de ouro"},{"diamond sword":"Espada de diamante"},{"netherite sword":"Espada de netherita"},{"glow berries":"Bagas brilhantes"},{"oak log":"Tronco de carvalho"},{"tinted glass":"Vidro fosco"},{"basalt":"Basalto"},{"polished basalt":"Basalto polido"},{"smooth basalt":"Basalto liso"},{"oak planks":"T\u00e1buas de carvalho"},{"copper block":"Bloco de cobre"},{"exposed copper block":"Bloco de cobre exposto"},{"weathered copper block":"Bloco de cobre desgastado"},{"oxidized copper block":"Bloco de cobre oxidado"},{"cut copper":"Cobre lapidado"},{"exposed cut copper":"Cobre lapidado exposto"},{"weathered cut copper":"Cobre lapidado desgastado"},{"oxidized cut copper":"Cobre lapidado oxidado"},{"waxed copper block":"Bloco de cobre encerado"},{"waxed exposed copper block":"Cobre exposto encerado "},{"waxed weathered copper block":"Cobre desgastado encerado"},{"waxed oxidized copper block":"Cobre oxidado encerado"},{"waxed cut copper":"Cobre lapidado encerado"},{"waxed exposed cut copper":"Cobre lapidado exposto encerado"},{"waxed weathered cut copper":"Cobre lapidado desgastado encerado"},{"waxed oxidized cut copper":"Cobre lapidado oxidado encerado"},{"item frame":"Moldura"},{"glow item frame":"Moldura brilhante"},{"anvil":"Bigorna"},{"stripped oak log":"Tronco de carvalo descascado"},{"rail":"Trilho"},{"powered rail":"Trilho el\u00e9trico"},{"detector rail":"Trilho detector"},{"activator rail":"Trilho ativador"},{"minecart":"Carrinho de mina"},{"saddle":"Sela"},{"chest minecart":"Carrinho de mina com ba\u00fa"},{"furnace minecart":"Carrinho de mina com fornalha"},{"tnt minecart":"Carrinho de mina com dinamite"},{"hopper minecart":"Carrinho de mina com funil"},{"elytra":"\u00c9litros"},{"oak boat":"Bote de carvalho"},{"spruce boat":"Bote de pinheiro"},{"birch boat":"Bote de b\u00e9tula"},{"jungle boat":"Bote de madeira da selva"},{"acacia boat":"Bote de ac\u00e1cia"},{"dark oak boat":"Bote de carvalho escuro"},{"melon slice":"Fatia de melancia"},{"dried kelp":"Algas secas"},{"bread":"P\u00e3o"},{"apple":"Ma\u00e7\u00e3"},{"beetroot":"Beterraba"},{"raw iron block":"Bloco de ferro bruto"},{"spider eye":"Olho de aranha"},{"oak door":"Porta de carvalho"},{"iron door":"Porta de ferro"},{"spruce door":"Porta de pinheiro"},{"birch door":"Porta de b\u00e9tula"},{"jungle door":"Porta de madeira da selva"},{"acacia door":"Porta de ac\u00e1cia"},{"dark oak door":"Porta de carvalho escuro"},{"crimson door":"Porta carmesim"},{"warped door":"Porta distorcida"},{"iron trapdoor":"Al\u00e7ap\u00e3o de ferro"},{"wooden trapdoor":"Al\u00e7ap\u00e3o de carvalho"},{"spruce trapdoor":"Al\u00e7ap\u00e3o de pinheiro"},{"birch trapdoor":"Al\u00e7ap\u00e3o de b\u00e9tula"},{"jungle trapdoor":"Al\u00e7ap\u00e3o de madeira da selva"},{"acacia trapdoor":"Al\u00e7ap\u00e3o de ac\u00e1cia"},{"dark oak trapdoor":"Al\u00e7ap\u00e3o de carvalho escuro"},{"crimson trapdoor":"Al\u00e7ap\u00e3o de carmesim"},{"warped trapdoor":"Al\u00e7ap\u00e3o distorcido"},{"fence gate":"Port\u00e3o de carvalho"},{"spruce fence gate":"Port\u00e3o de pinheiro"},{"birch fence gate":"Port\u00e3o de b\u00e9tula"},{"jungle fence gate":"Port\u00e3o de madeira da selva"},{"acacia fence gate":"Port\u00e3o de ac\u00e1cia"},{"dark oak fence gate":"Port\u00e3o de carvalho escuro"},{"crimson fence gate":"Port\u00e3o carmesim"},{"warped fence gate":"Port\u00e3o distorcido"},{"pumpkin pie":"Torta de ab\u00f3bora"},{"rabbit":"Coelho cru"},{"cooked rabbit":"Coelho assado"},{"tropical fish":"Peixe tropical"},{"pufferfish":"Baiacu"},{"mushroom stew":"Ensopado de cogumelos"},{"carrot":"Cenoura"},{"potato":"Batata"},{"granite":"Granito"},{"polished granite":"Granito polido"},{"polished andesite":"Andesito polido"},{"diorite":"Diorito"},{"polished diorite":"Diorito polido"},{"spruce planks":"T\u00e1buas de pinheiro"},{"birch planks":"T\u00e1buas de b\u00e9tula"},{"jungle planks":"T\u00e1buas de madeira da selva"},{"acacia planks":"T\u00e1buas de ac\u00e1cia"},{"dark oak planks":"T\u00e1buas de carvalho escuro"},{"spruce log":"Tronco de pinheiro"},{"birch log":"Tronco de b\u00e9tula"},{"jungle log":"Tronco de madeira da selva"},{"glass":"Vidro"},{"sponge":"Esponja"},{"wet sponge":"Esponja \u00famida"},{"acacia log":"Tronco de ac\u00e1cia"},{"dark oak log":"Tronco de carvalho escuro"},{"stripped spruce log":"Tronco de pinheiro descascado"},{"stripped birch log":"Tronco de b\u00e9tula descascado"},{"stripped jungle log":"Tronco de madeira da selva descascado"},{"stripped acacia log":"Tronco de ac\u00e1cia descascado"},{"stripped dark oak log":"Tronco de carvalho escuro descascado"},{"stripped crimson stem":"Tronco carmesim descascado"},{"stripped warped stem":"Tronco distorcido descascado"},{"oak wood":"Madeira de carvalho"},{"spruce wood":"Madeira de pinheiro"},{"birch wood":"Madeira de b\u00e9tula"},{"jungle wood":"Madeira da selva"},{"acacia wood":"Madeira de ac\u00e1cia"},{"dark oak wood":"Madeira de carvalho escuro"},{"stripped oak wood":"Madeira de carvalho descascada"},{"stripped spruce wood":"Madeira de pinheiro descascada"},{"stripped birch wood":"Madeira de b\u00e9tula descascada"},{"stripped jungle wood":"Madeira da selva descascada"},{"crimson hyphae":"Hifas carmesins"},{"warped hyphae":"Hifas distorcidas"},{"stripped crimson hyphae":"Hifas carmesins descascadas"},{"stripped warped hyphae":"Hifas distorcidas descascadas"},{"lapis block":"Bloco de l\u00e1pis-laz\u00fali"},{"iron block":"Bloco de ferro"},{"white wool":"L\u00e3 branca"},{"orange wool":"L\u00e3 laranja"},{"magenta wool":"L\u00e3 magenta"},{"light blue wool":"L\u00e3 azul-clara"},{"yellow wool":"L\u00e3 amarela"},{"lime wool":"L\u00e3 verde-lim\u00e3o"},{"pink wool":"L\u00e3 rosa"},{"gray wool":"L\u00e3 cinza"},{"light gray wool":"L\u00e3 cinza-clara"},{"cyan wool":"L\u00e3 ciano"},{"purple wool":"L\u00e3 roxa"},{"blue wool":"L\u00e3 azul"},{"brown wool":"L\u00e3 marrom"},{"green wool":"L\u00e3 verde"},{"red wool":"L\u00e3 vermelha"},{"black wool":"L\u00e3 preta"},{"oak slab":"Laje de carvalho"},{"cobweb":"Teia de aranha"},{"sea pickle":"Pepino-do-mar"},{"music disc pigstep":"Lena Raine - Pigstep"},{"netherixe axe":"Machado de netherita"},{"netherite shovel":"P\u00e1 de netherita"},{"netherite hoe":"Enxada de netherita"},{"netherite helmet":"Capacete de netherita"},{"netherite chestplate":"Peitoral de netherita"},{"netherite leggings":"Cal\u00e7as de netherita"},{"netherite boots":"Botas de netherita"},{"soul torch":"Tocha das almas"},{"soul campfire":"Fogueira das almas"},{"soul lantern":"Lampi\u00e3o das almas"},{"crimson fence":"Cerca carmesim"},{"warped fence":"Cerca distorcida"},{"respawn anchor":"\u00c2ncora de renascimento"},{"chain":"Correntes"},{"crimson planks":"T\u00e1buas carmesins"},{"warped planks":"T\u00e1buas distorcidas"},{"cracked nether bricks":"Tijolos do Nether rachados"},{"chiseled nether bricks":"Tijolos do Nether talhados"},{"gilded blackstone":"Pedra-negra dourada"},{"piglin banner pattern":"Focinho"},{"clay block":"Bloco de argila"},{"melon":"Melancia"},{"end stone":"Pedra do end"},{"end stone bricks":"Tijolos de pedra do End"},{"cracked deepslate tiles":"Ladrilhos de ard\u00f3sia rachados"},{"nether bricks":"Tijolos do nether"},{"cracked deepslate bricks":"Tijolos de ard\u00f3sia rachados"},{"mycelium":"Mic\u00e9lio"},{"stone brick stairs":"Escadas de tijolos de pedra"},{"brick stairs":"Escadas de tijolos"},{"nether bricks stairs":"Escadas de tijolos do nether"},{"cobblestone stairs":"Escadas de pedregulho"},{"spruce stairs":"Escadas de pinheiro"},{"spruce slab":"Laje de pinheiro"},{"birch slab":"Laje de b\u00e9tula"},{"jungle slab":"Laje de madeira da selva"},{"acacia slab":"Laje de ac\u00e1cia"},{"dark oak slab":"Laje de carvalho escuro"},{"crimson slab":"Laje carmesin"},{"warped slab":"Laje distorcida"},{"stone slab":"Laje de pedra"},{"smooth stone slab":"Laje de pedra lisa"},{"sandstone slab":"Laje de arenito"},{"cut sandstone slab":"Laje de arenito cortado"},{"petrified oak slab":"Laje de carvalho petrificado"},{"cobblestone slab":"Laje de pedregulho"},{"bricks slab":"Laje de tijolos"},{"stone brick slab":"Laje de tijolos de pedra"},{"nether bricks slab":"Laje de tijolos do nether"},{"quartz slab":"Laje de quartzo"},{"red sandstone slab":"Laje de arenito vermelho"},{"cut red sandstone slab":"Laje de arenito vermelho cortado"},{"purpur slab":"Laje de p\u00farpura"},{"prismarine slab":"Laje de prismarinho"},{"prismarine brick slab":"Laje de tijolos de prismarinho"},{"dark prismarine slab":"Laje de prismarinho escuro"},{"smooth quartz":"Bloco de quartzo liso"},{"bricks":"Tijolos"},{"smooth stone":"Pedra lisa"},{"bookshelf":"Estante de livros"},{"mossy cobblestone":"Pedregulho musgoso"},{"purpur block":"Bloco de p\u00farpura"},{"purpur pillar":"Pilar de p\u00farpura"},{"quartz block":"Bloco de quartzo"},{"chiseled quartz block":"Bloco de quartzo talhado"},{"quartz bricks":"Tijolos de quartzo"},{"quartz pillar":"Pilar de quartzo"},{"quartz stairs":"Escadas de quartzo"},{"crimson stairs":"Escadas carmesins"},{"warped stairs":"Escadas distorcidas"},{"white terracotta":"Terracota branca"},{"orange terracotta":"Terracota laranja"},{"magenta terracotta":"Terracota magenta"},{"light blue terracotta":"Terracota azul-clara"},{"yellow terracotta":"Terracota amarela"},{"lime terracotta":"Terracota verde-lim\u00e3o"},{"pink terracotta":"Terracota rosa"},{"gray terracotta":"Terracota cinza"},{"light gray terracotta":"Terracota cinza-clara"},{"cyan terracotta":"Terracota ciano"},{"purple terracotta":"Terracota roxa"},{"blue terracotta":"Terracota azul"},{"brown terracotta":"Terracota marrom"},{"green terracotta":"Terracota verde"},{"red terracotta":"Terracota vermelha"},{"black terracotta":"Terracota preta"},{"terracotta":"Terracota"},{"coal block":"Bloco de carv\u00e3o"},{"hay block":"Fardo de feno"},{"acacia stairs":"Escadas de ac\u00e1cia"},{"dark oak stairs":"Escadas de carvalho escuro"},{"jungle stairs":"Escadas de madeira da selva"},{"prismarine":"Prismarinho"},{"prismarine bricks":"Tijolos de prismarinho"},{"dark prismarine":"Prismarinho escuro"},{"red nether brick":"Tijolos vermelhos do nether"},{"magma block":"Bloco de magma"},{"prismarine stairs":"Escadas de prismarinho"},{"prismarine brick stairs":"Escadas de tijolos de prismarinho"},{"dark prismarine stairs":"Escadas de primarinho escuro"},{"bone block":"Bloco de ossos"},{"white concrete":"Concreto branco"},{"orange concrete":"Concreto laranja"},{"magenta concrete":"Concreto magenta"},{"light blue concrete":"Concreto azul-claro"},{"yellow concrete":"Concreto amarelo"},{"lime concrete":"Concreto verde-lim\u00e3o"},{"pink concrete":"Concreto rosa"},{"gray concrete":"Concreto cinza"},{"light gray concrete":"Concreto cinza-claro"},{"cyan concrete":"Concreto ciano"},{"purple concrete":"Concreto roxo"},{"blue concrete":"Concreto azul"},{"brown concrete":"Concreto marrom"},{"green concrete":"Concreto verde"},{"red concrete":"Concreto vermelho"},{"black concrete":"Concreto preto"},{"white concrete powder":"Cimento branco"},{"orange concrete powder":"Cimento laranja"},{"magenta concrete powder":"Cimento magenta"},{"light blue concrete powder":"Cimento azul-claro"},{"yellow concrete powder":"Cimento amarelo"},{"lime concrete powder":"Cimento verde-lim\u00e3o"},{"pink concrete powder":"Cimento rosa"},{"gray concrete powder":"Cimento cinza"},{"light gray concrete powder":"Cimento cinza-claro"},{"cyan concrete powder":"Cimento ciano"},{"purple concrete powder":"Cimento roxo"},{"blue concrete powder":"Cimento azul"},{"brown concrete powder":"Cimento marrom"},{"green concrete powder":"Cimento verde"},{"red concrete powder":"Cimento vermelho"},{"black concrete powder":"Cimento preto"},{"dead tube coral block":"Bloco de coral-de-tubo morto"},{"dead brain coral block":"Bloco de coral-de-c\u00e9rebro morto"},{"dead bubble coral block":"Bloco de coral-de-bolha morto"},{"dead fire coral block":"Bloco de coral-de-fogo morto"},{"dead horn coral block":"Bloco de coral-de-chifre morto"},{"tube coral block":"Bloco de coral-de-tubo"},{"brain coral block":"Bloco de coral-de-c\u00e9rebro"},{"bubble coral block":"Bloco de coral-de-bolha"},{"fire coral block":"Bloco de coral-de-fogo"},{"horn coral block":"Bloco de coral-de-chifre"},{"polished granite stairs":"Escadas de granito polido"},{"smooth red sandstone stairs":"Escadas de arenito vermelho liso"},{"mossy stone brick stairs":"Escadas de tijolos de pedra musgosos"},{"polished diorite stairs":"Escadas de diorito polido"},{"mossy cobblestone stairs":"Escadas de pedregulho musgoso"},{"end stone stairs":"Escadas de tijolos de pedra do end"},{"stone stairs":"Escadas de pedra"},{"smooth quartz stair":"Escadas de quartzo liso"},{"granite stairs":"Escadas de granito"},{"andesite stairs":"Escadas de andesito"},{"red nether brick stairs":"Escadas de tijolos do nether vermelhos"},{"polished andesite stairs":"Escadas de andesito polido"},{"diorite stairs":"Escadas de diorito"},{"cobbled deepslate stairs":"Escadas de pedregulo de ard\u00f3sia"},{"polished deepslate stairs":"Escadas de ard\u00f3sia polida"},{"deepslate tile stairs":"Escadas de ladrilhos de ard\u00f3sia"},{"deepslate brick stairs":"Escadas de tijolos de ard\u00f3sia"},{"polished granite slab":"Laje de granito polido"},{"smooth red sandstone slab":"Laje de arenito vermelho liso"},{"mossy stone bricks slab":"Laje de tijolos de pedra musgosos"},{"polished diorite slab":"Laje de diorito polido"},{"mossy cobblestone slab":"Laje de pedregulho musgoso"},{"end stone bricks slab":"Laje de tijolos do end"},{"smooth sandstone slab":"Laje de arenito liso"},{"smooth quartz slab":"Laje de quartzo liso"},{"granite slab":"Laje de granito"},{"andesite slab":"Laje de andesito"},{"red nether brick slab":"Laje de tijolos vermelhos do nether"},{"polished andesite slab":"Laje de andesito polido"},{"diorite slab":"Laje de diorito"},{"cobbled deepslate slab":"Laje de pedregulo de ard\u00f3sia"},{"polished deepslate slab":"Laje de ard\u00f3sia polida"},{"deepslate brick slab":"Laje de tijolos de ard\u00f3sia"},{"deepslate tile slab":"Laje de ladrilhos de ard\u00f3sia"},{"dried kelp block":"Bloco de algas secas"},{"blackstone slab":"Laje de pedra-negra"},{"blackstone stairs":"Escadas de pedra-negra"},{"polished blackstone slab":"Laje de pedra-negra polida"},{"polished blackstone stairs":"Escadas de pedra-negra polida"},{"polished blackstone brick slab":"Laje de tijolos de pedra-negra polida"},{"polished blackstone brick stairs":"Escadas de tijolos de pedra-negra polida"},{"cut copper stairs":"Escadas de cobre lapidado"},{"exposed cut copper stairs":"Escadas de cobre lapidado exposto"},{"weathered cut copper stairs":"Escadas de cobre lapidado desgastado"},{"oxidized cut copper stairs":"Escadas de cobre lapidado oxidado"},{"waxed cut copper stairs":"Escadas de cobre lapidado encerado"},{"waxed exposed cut copper stairs":"Escadas de cobre lapidado exposto encerado"},{"waxed weathered cut copper stairs":"Escadas de cobre lapidado desgastado encerado"},{"waxed oxidized cut copper stairs":"Escadas de cobre lapidado oxidado encerado"},{"cut copper slab":"Laje de cobre lapidado"},{"exposed cut copper slab":"Laje de cobre lapidado exposto"},{"weathered cut copper slab":"Laje de cobre lapidado desgastado"},{"oxidized cut copper slab":"Laje de cobre lapidado oxidado"},{"waxed cut copper slab":"Laje de cobre lapidado encerado"},{"waxed exposed cut copper slab":"Laje de cobre lapidado exposto encerado"},{"waxed weathered cut copper slab":"Laje de cobre lapidado desgastado encerado"},{"waxed oxidized cut copper slab":"Laje de cobre lapidado oxidado encerado"},{"dripstone block":"Bloco de espeleotema"},{"diamond helmet":"Capacete de diamante"},{"lapis lazuli":"L\u00e1pis-laz\u00fali"},{"map":"Mapa em branco"},{"wooden axe":"Machado de madeira"},{"jukebox":"Toca-discos"},{"arrow":"Flecha"},{"fern":"Samambaia"},{"grass":"Grama"},{"seagrass":"Erva marinha"},{"dead bush":"Arbusto seco"},{"oak sapling":"Muda de carvalho"},{"birch sapling":"Muda de b\u00e9tula"},{"jungle sapling":"Muda de \u00e1rvore da selva"},{"acacia sapling":"Muda de ac\u00e1cia"},{"dark oak sapling":"Muda de carvalho escuro"},{"yellow flower":"Dente-de-le\u00e3o"},{"poppy":"Papoula"},{"blue orchid":"Orqu\u00eddea Azul"},{"allium":"Alho-silvestre"},{"azure bluet":"Flor-silvestre-azul"},{"red tulip":"Tulipa vermelha"},{"orange tulip":"Tulipa laranja"},{"white tulip":"Tulipa branca"},{"pink tulip":"Tulipa rosa"},{"oxeye daisy":"Margarida"},{"cornflower":"Cent\u00e1urea"},{"spore blossom":"Flor de esporos"},{"lily of the valley":"L\u00edrio do vale"},{"wither rose":"Rosa do wither"},{"hanging roots":"Ra\u00edzes a\u00e9reas"},{"kelp":"Alga"},{"glowstone dust":"P\u00f3 de pedra luminosa"},{"white dye":"Corante branco"},{"glass pane":"Painel de vidro"},{"infested stone":"Pedra infestada"},{"infested cobblestone":"Pedregulho infestado"},{"infested stone bricks":"Tijolos de pedra infestados"},{"infested mossy stone bricks":"Tijolos de pedra musgosos infestados"},{"infested chiseled stone bricks":"Tijolos de pedra talhados infestado"},{"infested cracked stone bricks":"Tijolos de pedra rachados infestados"},{"infested deepslate":"Ard\u00f3sia infestada"},{"brown mushroom block":"Bloco de Cogumelo Marrom"},{"mushroom stem":"Caule de cogumelo"},{"red mushroom block":"Bloco de Cogumelo Vermelho"},{"torch":"Tocha"},{"vine":"Trepadeiras"},{"lily pad":"Vit\u00f3ria-r\u00e9gia"},{"iron bars":"Grades de ferro"},{"fermented spider eye":"Olho de aranha fermentado"},{"ender pearl":"P\u00e9rola de ender"},{"phantom membrane":"Membrana de phantom"},{"chipped anvil":"Bigorna danificada"},{"cartography table":"Bancada de cartografia"},{"stonecutter":"Cortador de pedras"},{"loom":"Tear"},{"shulker shell":"Casco de shulker"},{"heart of the sea":"Cora\u00e7\u00e3o do mar"},{"jungle leaves":"Folhas da selva"},{"nautilus shell":"Concha de n\u00e1utilo"},{"music disc wait":"C418 - wait"},{"music disc 13":"C418 - 13"},{"music disc cat":"C418 - cat"},{"music disc blocks":"C418 - blocks"},{"music disc chirp":"C418 - chirp"},{"music disc far":"C418 - far"},{"music disc mall":"C418 - mall"},{"music disc mellohi":"C418 - mellohi"},{"music disc stal":"C418 - stal"},{"music disc strad":"C418 - strad"},{"music disc ward":"C418 - ward\t"},{"music disc 11":"C418 - 11"},{"iron nugget":"Pepita de ferro"},{"raw copper block":"Bloco de cobre bruto"},{"raw gold block":"Bloco de ouro bruto"},{"goat spawn egg":"Ovo gerador de cabra"},{"squid spawn egg":"Ovo gerador de lula"},{"bat spawn egg":"Ovo gerador de morcego"},{"blaze spawn egg":"Ovo gerador de blaze"},{"cat spawn egg":"Ovo gerador de gato"},{"cave spider spawn egg":"Ovo gerador de aranha das cavernas"},{"stone axe":"Machado de pedra"},{"iron axe":"Machado de ferro"},{"golden axe":"Machado de ouro"},{"diamond axe":"Machado de diamante"},{"wooden shovel":"P\u00e1 de madeira"},{"stone shovel":"P\u00e1 de pedra"},{"iron shovel":"P\u00e1 de ferro"},{"golden shovel":"P\u00e1 de ouro"},{"diamond shovel":"P\u00e1 de diamante"},{"wooden hoe":"Enxada de madeira"},{"iron hoe":"Enxada de ferro"},{"golden hoe":"Enxada de ouro"},{"diamond hoe":"Enxada de diamante"},{"compass":"B\u00fassola"},{"amethyst shard":"Fragmento de ametista"},{"flower banner pattern":"Figura de flor"},{"creeper banner pattern":"Figura de creeper"},{"banner pattern":"Figura de caveira"},{"mojang banner pattern":"S\u00edmbolo"},{"globe banner pattern":"Globo"},{"chorus fruit":"Fruta do coro"},{"popped chorus fruit":"Fruta do coro cozida"},{"leather horse armor":"Armadura de couro para cavalo"},{"iron horse armor":"Armadura de ferro para cavalo"},{"golden horse armor":"Armadura de ouro para cavalo"},{"diamond horse armor":"Armadura de diamante para cavalo"},{"rabbit hide":"Pele de coelho"},{"prismarine crystals":"Cristais de prismarinho"},{"prismarine shard":"Fragmento de prismarinho"},{"quartz":"Quartzo do Nether"},{"nether brick":"Tijolo do nether"},{"firework star":"Estrela de fogo de artif\u00edcio"},{"firework rocket":"Fogo de artif\u00edcio"},{"beetroot seeds":"Sementes de beterraba"},{"fire charge":"Bola de fogo"},{"writable book":"Livro e pena"},{"ender eye":"Olho de ender"},{"nether wart":"Fungo do nether"},{"bone":"Osso"},{"bone meal":"Farinha de osso"},{"sugar":"A\u00e7ucar"},{"pumpkin seeds":"Sementes de ab\u00f3bora"},{"melon seeds":"Sementes de melancia"},{"ladder":"Escada de m\u00e3o"},{"big dripleaf":"Plantaforma grande"},{"small dripleaf block":"Plantaforma pequena"},{"dead chorus flower":"Flor do coro morta"},{"chorus flower":"Flor do coro"},{"chest":"Ba\u00fa"},{"cactus":"Cacto"},{"oak fence":"Cerca de carvalho"},{"spruce fence":"Cerca de pinheiro"},{"birch fence":"Cerca de b\u00e9tula"},{"jungle fence":"Cerca de madeira da selva"},{"acacia fence":"Cerca de ac\u00e1cia"},{"dark oak fence":"Cerca de carvalho escuro"},{"farmland":"Terra arada"},{"end lamp":"Bast\u00e3o do fim"},{"pointed dripstone":"Espeleotema pontiagudo"},{"small amethyst bud":"Cristal de ametista pequeno"},{"medium amethyst bud":"Cristal de ametista m\u00e9dio"},{"large amethyst bud":"Cristal de ametista grande"},{"lantern":"Lampi\u00e3o"},{"composter":"Composteira"},{"barrel":"Barril"},{"grindstone":"Rebolo"},{"bell":"Sino"},{"campfire":"Fogueira"},{"candle":"Vela"},{"white candle":"Vela branca"},{"orange candle":"Vela laranja"},{"magenta candle":"Vela magenta"},{"light blue candle":"Vela azul-clara"},{"yellow candle":"Vela amarela"},{"lime candle":"Vela verde-lim\u00e3o"},{"pink candle":"Vela rosa"},{"gray candle":"Vela cinza"},{"light gray candle":"Vela cinza-clara"},{"cyan candle":"Vela ciano"},{"purple candle":"Vela roxa"},{"blue candle":"Vela azul"},{"brown candle":"Vela marrom"},{"green candle":"Vela verde"},{"red candle":"Vela vermelha"},{"black candle":"Vela preta"},{"white banner":"Estandarte branco"},{"orange banner":"Estandarte laranja"},{"magenta banner":"Estandarte magenta"},{"light blue banner":"Estandarte azul-claro"},{"yellow banner":"Estandarte amarelo"},{"lime banner":"Estandarte verde-lim\u00e3o"},{"pink banner":"Estandarte rosa"},{"gray banner":"Estandarte cinza"},{"light gray banner":"Estandarte cinza-claro"},{"cyan banner":"Estandarte ciano"},{"purple banner":"Estandarte roxo"},{"blue banner":"Estandarte azul"},{"brown banner":"Estandarte marrom"},{"green banner":"Estandarte verde"},{"red banner":"Estandarte vermelho"},{"black banner":"Estandarte preto"},{"armor stand":"Suporte de armaduras"},{"dragon head":"Cabe\u00e7a de drag\u00e3o"},{"skeleton skull":"Cr\u00e2nio de esqueleto"},{"wither skeleton skull":"Cr\u00e2nio de esqueleto wither"},{"player head":"Cabe\u00e7a"},{"zombie head":"Cabe\u00e7a de zumbi"},{"creeper head":"Cabe\u00e7a de creeper"},{"flower pot":"Vaso"},{"white bed":"Cama branca"},{"orange bed":"Cama laranja"},{"magenta bed":"Cama magenta"},{"light blue bed":"Cama azul-clara"},{"yellow bed":"Cama amarela"},{"lime bed":"Cama verde-lim\u00e3o"},{"pink bed":"Cama rosa"},{"gray bed":"Cama cinza"},{"light gray bed":"Cama cinza-clara"},{"cyan bed":"Cama ciano"},{"purple bed":"Cama roxa"},{"blue bed":"Cama azul"},{"brown bed":"Cama marrom"},{"green bed":"Cama verde"},{"red bed":"Cama vermelha"},{"black bed":"Cama preta"},{"oak sign":"Placa de carvalho"},{"spruce sign":"Placa de pinheiro"},{"birch sign":"Placa de b\u00e9tula"},{"jungle sign":"Placa de madeira da selva"},{"acacia sign":"Placa de ac\u00e1cia"},{"dark oak sign":"Placa de carvalho escuro"},{"crimson sign":"Placa carmesin"},{"warped sign":"Placa distorcida"},{"painting":"Quadro"},{"scaffold":"Andaime"},{"enchanting table":"Mesa de encantamentos"},{"ender chest":"Ba\u00fa de ender"},{"damaged anvil":"Bigorna muito danificada"},{"cobblestone wall":"Muro de pedregulho"},{"mossy cobblestone wall":"Muro de pedregulho musgoso"},{"brick wall":"Muro de tijolos"},{"prismarine wall":"Muro de prismarinho"},{"red sandstone wall":"Muro de arenito vermelho"},{"mossy stone brick wall":"Muro de tijolos de pedra musgosos"},{"granite wall":"Muro de granito"},{"stone brick wall":"Muro de tijolos de pedra"},{"nether brick wall":"Muro de tijolos do nether"},{"andesite wall":"Muro de andesito"},{"red nether brick wall":"Muro de tijolos vermelhos do nether"},{"sandstone wall":"Muro de arenito"},{"end stone brick wall":"Muro de tijolos de pedra do end"},{"diorite wall":"Muro de diorito"},{"blackstone wall":"Muro de pedra-negra"},{"polished blackstone wall":"Muro de pedra-negra polida"},{"polished blackstone brick wall":"Muro de tijolos de pedra-negra polida"},{"cobbled deepslate wall":"Muro de pedregulho de ard\u00f3sia"},{"polished deepslate wall":"Muro de ard\u00f3sia polida"},{"deepslate brick wall":"Muro de tijolos de ard\u00f3sia"},{"deepslate tile wall":"Muro de ladrilhos de ard\u00f3sia"},{"nether brick fence":"Cerca de tijolos do nether"},{"white carpet":"Tapete branco"},{"orange carpet":"Tapete laranja"},{"magenta carpet":"Tapete magenta"},{"light blue carpet":"Tapete azul-claro"},{"yellow carpet":"Tapete amarelo"},{"lime carpet":"Tapete verde-lim\u00e3o"},{"pink carpet":"Tapete rosa"},{"gray carpet":"Tapete cinza"},{"light gray carpet":"Tapete cinza-claro"},{"cyan carpet":"Tapete ciano"},{"purple carpet":"Tapete roxo"},{"blue carpet":"Tapete azul"},{"brown carpet":"Tapete marrom"},{"green carpet":"Tapete verde"},{"red carpet":"Tapete vermelho"},{"black carpet":"Tapete preto"},{"dirt path":"Caminho de terra"},{"sunflower":"Girassol"},{"lilac":"Lil\u00e1s"},{"rose bush":"Roseira"},{"peony":"Pe\u00f4nia"},{"tall grass":"Grama alta"},{"large fern":"Samambaia grande"},{"shulker box":"Caixa de shulker"},{"white shulker box":"Caixa de shulker branca"},{"orange shulker box":"Caixa de shulker laranja"},{"magenta shulker box":"Caixa de shulker magenta"},{"light blue shulker box":"Caixa de shulker azul-clara"},{"yellow shulker box":"Caixa de shulker amarela"},{"lime shulker box":"Caixa de shulker verde-lim\u00e3o"},{"pink shulker box":"Caixa de shulker rosa"},{"gray shulker box":"Caixa de shulker cinza"},{"light gray shulker box":"Caixa de shulker cinza-clara"},{"cyan shulker box":"Caixa de shulker ciano"},{"purple shulker box":"Caixa de shulker roxa"},{"blue shulker box":"Caixa de shulker azul"},{"brown shulker box":"Caixa de shulker marrom"},{"green shulker box":"Caixa de shulker verde"},{"red shulker box":"Caixa de shulker vermelha"},{"black shulker box":"Caixa de shulker preta"},{"white glazed terracotta":"Azulejo branco"},{"orange glazed terracotta":"Azulejo laranja"},{"magenta glazed terracotta":"Azulejo magenta"},{"light blue glazed terracotta":"Azulejo azul-claro"},{"yellow glazed terracotta":"Azulejo amarelo"},{"lime glazed terracotta":"Azulejo verde-lim\u00e3o"},{"pink glazed terracotta":"Azulejo rosa"},{"gray glazed terracotta":"Azulejo cinza"},{"light gray glazed terracotta":"Azulejo cinza-claro"},{"cyan glazed terracotta":"Azulejo ciano"},{"purple glazed terracotta":"Azulejo roxo"},{"blue glazed terracotta":"Azulejo azul"},{"brown glazed terracotta":"Azulejo marrom"},{"green glazed terracotta":"Azulejo verde"},{"red glazed terracotta":"Azulejo vermelho"},{"black glazed terracotta":"Azulejo preto"},{"orange dye":"Corante laranja"},{"magenta dye":"Corante magenta"},{"light blue dye":"Corante azul-claro"},{"yellow dye":"Corante amarelo"},{"lime dye":"Corante verde-lim\u00e3o"},{"pink dye":"Corante rosa"},{"gray dye":"Corante cinza"},{"light gray dye":"Corante cinza-claro"},{"cyan dye":"Corante ciano"},{"purple dye":"Corante roxo"},{"blue dye":"Corante azul"},{"brown dye":"Corante marrom"},{"green dye":"Corante verde"},{"red dye":"Corante vermelho"},{"black dye":"Corante preto"},{"rabbit foot":"P\u00e9 de coelho"},{"cauldron":"Caldeir\u00e3o"},{"magma cream":"Creme de magma"},{"splash potion":"Frasco de \u00e1gua arremess\u00e1vel"},{"splash potion":"Frasco arremess\u00e1vel estranha"},{"splash potion":"Po\u00e7\u00e3o arremess\u00e1vel espessa"},{"splash potion":"Po\u00e7\u00e3o arremess\u00e1vel comum"},{"zombie horse spawn egg":"Ovo gerador de cavalo-zumbi"},{"zombie villager spawn egg":"Ovo gerador de alde\u00e3o zumbi"},{"zombified piglin spawn egg":"Ovo gerador de piglin-zumbi"},{"chicken spawn egg":"Ovo gerador de galinha"},{"cod spawn egg":"Ovo gerador de bacalhau"},{"cow spawn egg":"Ovo gerador de vaca"},{"creeper spawn egg":"Ovo gerador de creeper"},{"dolphin spawn egg":"Ovo gerador de golfinho"},{"donkey spawn egg":"Ovo gerador de burro"},{"drowned spawn egg":"Ovo gerador de afogado"},{"elder guardian spawn egg":"Ovo gerador de guardi\u00e3o-mestre"},{"enderman spawn egg":"Ovo gerador de enderman"},{"endermite spawn egg":"Ovo gerador de endermite"},{"evoker spawn egg":"Ovo gerador de invocador"},{"fox spawn egg":"Ovo gerador de raposa"},{"ghast spawn egg":"Ovo gerador de ghast"},{"guardian spawn egg":"Ovo gerador de guardi\u00e3o"},{"hoglin spawn egg":"Ovo gerador de hoglin"},{"horse spawn egg":"Ovo gerador de cavalo"},{"husk spawn egg":"Ovo gerador de zumbi-m\u00famia"},{"llama spawn egg":"Ovo gerador de lhama"},{"magma cube spawn egg":"Ovo gerador de cubo de magma"},{"mooshroom spawn egg":"Ovo gerador de coguvaca"},{"mule spawn egg":"Ovo gerador de mula"},{"ocelot spawn egg":"Ovo gerador de jaguatirica"},{"panda spawn egg":"Ovo gerador de panda"},{"parrot spawn egg":"Ovo gerador de papagaio"},{"phantom spawn egg":"Ovo gerador de phantom"},{"pig spawn egg":"Ovo gerador de porco"},{"piglin spawn egg":"Ovo gerador de piglin"},{"piglin brute spawn egg":"Ovo gerador de piglin b\u00e1rbaro"},{"pillager spawn egg":"Ovo gerador de saqueador"},{"polar bear spawn egg":"Ovo gerador de urso polar"},{"pufferfish spawn egg":"Ovo gerador de baiacu"},{"rabbit spawn egg":"Ovo gerador de coelho"},{"ravager spawn egg":"Ovo gerador de devastador"},{"salmon spawn egg":"Ovo gerador de salm\u00e3o"},{"sheep spawn egg":"Ovo gerador de ovelha"},{"shulker spawn egg":"Ovo gerador de shulker"},{"silverfish spawn egg":"Ovo gerador de tra\u00e7a"},{"skeleton spawn egg":"Ovo gerador de esqueleto"},{"turtle spawn egg":"Ovo gerador de tartaruga"},{"tropical fish spawn egg":"Ovo gerador de peixe tropical"},{"trader llama spawn egg":"Ovo gerador de lhama do vendedor"},{"strider spawn egg":"Ovo gerador de lavagante"},{"stray spawn egg":"Ovo gerador de esqueleto-errante"},{"spider spawn egg":"Ovo gerador de aranha"},{"slime spawn egg":"Ovo gerador de slime"},{"skeleton horse spawn egg":"Ovo gerador de cavalo-esqueleto"},{"iron helmet":"Capacete de ferro"},{"golden helmet":"Capacete de ouro"},{"leather helmet":"Capacete de couro"},{"chainmail helmet":"Capacete de malha"},{"turtle helmet":"Casco de tartaruga"},{"diamond chestplate":"Peitoral de diamante"},{"iron chestplate":"Peitoral de ferro"},{"golden chestplate":"Peitoral de ouro"},{"leather chestplate":"Peitoral de couro"},{"chainmail chestplate":"Peitoral de malha"},{"diamond boots":"Botas de diamante"},{"iron boots":"Botas de ferro"},{"golden boots":"Botas de ouro"},{"leather boots":"Botas de couro"},{"chainmail boots":"Botas de malha"},{"diamond leggings":"Cal\u00e7as de diamante"},{"iron leggings":"Cal\u00e7as de ferro"},{"golden leggings":"Cal\u00e7as de ouro"},{"leather leggings":"Cal\u00e7as de couro"},{"chainmail leggings":"Cal\u00e7as de malha"},{"bow":"Arco"},{"trident":"Tridente"},{"totem of undying":"Totem da imortalidade"},{"spectral arrow":"Flecha espectral"},{"tipped arrow":"Flecha de vis\u00e3o noturna"},{"tipped arrow":"Flecha de vis\u00e3o noturna 2"},{"tipped arrow":"Flecha de invisibilidade"},{"tipped arrow":"Flecha de invisibilidade 2"},{"tipped arrow":"Flecha de salto"},{"tipped arrow":"Flecha de salto 2"},{"tipped arrow":"Flecha de salto 3"},{"tipped arrow":"Flecha de resist\u00eancia ao fogo"},{"tipped arrow":"Flecha de resist\u00eancia ao fogo 2"},{"tipped arrow":"Flecha de agilidade"},{"tipped arrow":"Flecha de agilidade 2"},{"tipped arrow":"Flecha de agilidade 3"},{"tipped arrow":"Flecha de lentid\u00e3o"},{"tipped arrow":"Flecha de lentid\u00e3o 2"},{"tipped arrow10":"Flecha de lentid\u00e3o 3"},{"tipped arrow":"Flecha do mestre-tartaruga"},{"tipped arrow":"Flecha do mestre-tartaruga 2"},{"tipped arrow":"Flecha do mestre-tartaruga 3"},{"tipped arrow":"Flecha de respira\u00e7\u00e3o aqu\u00e1tica"},{"tipped arrow":"Flecha de respira\u00e7\u00e3o aqu\u00e1tica 2"},{"tipped arrow":"Flecha de cura"},{"tipped arrow":"Flecha de cura 2"},{"tipped arrow":"Flecha de dano"},{"tipped arrow":"Flecha de dano 2"},{"tipped arrowx":"Flecha de veneno"},{"tipped arrow":"Flecha de veneno 2"},{"tipped arrow":"Flecha de veneno 3"},{"tipped arrow":"Flecha de regenera\u00e7\u00e3o"},{"tipped arrow":"Flecha de regenera\u00e7\u00e3o 2"},{"tipped arrow":"Flecha de regenera\u00e7\u00e3o 3"},{"tipped arrow":"Flecha de for\u00e7a"},{"tipped arrow":"Flecha de for\u00e7a 2"},{"tipped arrow":"Flecha de for\u00e7a 3"},{"tipped arrow":"Flecha de fraqueza"},{"tipped arrow":"Flecha de fraqueza 2"},{"tipped arrow":"Flecha de sorte"},{"tipped arrow":"Flecha de queda lenta"},{"tipped arrow":"Flecha de queda lenta 2"},{"oak leaves":"Folhas de carvalho"},{"spruce leaves":"Folhas de pinheiro"},{"birch leaves":"Folhas de b\u00e9tula"},{"acacia leaves":"Folhas de ac\u00e1cia"},{"dark oak leaves":"Folhas de carvalho escuro"},{"azalea leaves":"Folhas de azaleia"},{"flowering azalea leaves":"Folhas de azaleia florescente"},{"sugar cane":"Cana-de-a\u00e7\u00facar"},{"bamboo":"Bambu"}]